{
  "FirstCoolingPump": [
    {
      "P": "0.0",
      "Sta": "0.0",
      "DeviceId": "002ac93d7f6b483d9563abac51a2ba84",
      "冷温水泵1": "0.0921875",
      "Freq": "0.0921875",
      "ConsTotal": "32311.92",
      "Name": "冷温水泵1#"
    },
    {
      "冷冻水泵2": "0.09375",
      "P": "0.0",
      "Sta": "0.0",
      "DeviceId": "cbc096e9a5f04f21a3096f83cc38eaaa",
      "Freq": "0.096875",
      "ConsTotal": "156185.84",
      "Name": "冷温水泵2#"
    },
    {
      "P": "0.0",
      "Sta": "0.0",
      "冷冻水泵3": "0.2921875",
      "DeviceId": "b8ad2fadb3d44ad88b48f2d3aa21db9e",
      "Freq": "0.2953125",
      "ConsTotal": "330197.22",
      "Name": "冷温水泵3#"
    },
    {
      "P": "42.0",
      "Sta": "1.0",
      "冷冻水泵4": "46.198437",
      "冷冻水泵3": "45.504684",
      "DeviceId": "ed322d3170e541b187ede1dfeeb2aba3",
      "Freq": "46.162502",
      "ConsTotal": "224221.2",
      "Name": "冷温水泵4#"
    }
  ],
  "ChillingTower": [
    {
      "Sta": "0.0",
      "DeviceId": "6cfde2108efa4c5292a101cc0f3f1ef8",
      "Freq": "0.115",
      "Name": "6号冷却塔"
    },
    {
      "P": "0.0",
      "Sta": "0.0",
      "DeviceId": "5be32d14de7b4e5286ac62faad67bb4f",
      "Freq": "0.115",
      "ConsTotal": "17498.96",
      "Name": "5号冷却塔"
    },
    {
      "Sta": "0.0",
      "DeviceId": "b5ab49b39dd346e3b60b1bc511cb2ce3",
      "Freq": "0.115",
      "Name": "4号冷却塔"
    },
    {
      "P": "1.09",
      "Sta": "1.0",
      "DeviceId": "d5a11eb1676f499585ab404254aa4bb9",
      "Freq": "33.155",
      "ConsTotal": "18797.34",
      "Name": "3号冷却塔"
    },
    {
      "Sta": "0.0",
      "DeviceId": "65dec05ffad3405abd6ecf75e7266871",
      "Freq": "0.53",
      "Name": "2号冷却塔"
    },
    {
      "P": "0.05",
      "Sta": "0.0",
      "DeviceId": "f164bf00640a4a5782396e733c599c04",
      "Freq": "0.23",
      "ConsTotal": "3318.61",
      "Name": "1号冷却塔"
    }
  ],
  "Unit": [
    {
      "Sta": "1.0",
      "DeviceId": "beca07bd4f064c1f9f0f413054a10bb6",
      "1#冷机冷却进水温度": "0.0",
      "Name": "冷机1#",
      "T21": "24.387499",
      "T20": "-25.0",
      "T22": "24.3375",
      "T25": "22.2125",
      "ReCoLWT": "12.0",
      "T27": "22.225",
      "T26": "27.781252",
      "T29": "27.731249",
      "T28": "29.20625",
      "ChEWT": "25.381248",
      "EvaAT": "10.7",
      "T5": "21.4375",
      "T6": "12.6875",
      "T7": "13.018749",
      "ChLWT": "26.925001",
      "T9": "16.90625",
      "T30": "-74.88125",
      "ConAT": "27.1",
      "T10": "18.84375",
      "T32": "26.587502",
      "T31": "31.90625",
      "CoEWT": "13.4",
      "T14": "24.706251",
      "T15": "24.61875",
      "CoLWT": "12.18125",
      "2#冷机冷却进水温度": "0.0"
    },
    {
      "EvaAT": "23.4",
      "ConAT": "25.9",
      "Sta": "0.0",
      "ChLWT": "27.825",
      "CoEWT": "24.2",
      "DeviceId": "7606905e0226494f8b2b0ca0ebc50626",
      "ReCoLWT": "10.0",
      "ChEWT": "27.34375",
      "CoLWT": "18.981249",
      "Name": "冷机2#"
    }
  ],
  "System": {
    "p": "32310.4",
    "OutT": "20.58125",
    "ChLWT": "27.825",
    "CoEWT": "63.5625",
    "H": "48.506252",
    "ChEWT": "27.34375",
    "WT": "10.63711",
    "CoLWT": "12.1"
  },
  "ChillingPump": [
    {
      "P": "26.6",
      "Sta": "1.0",
      "DeviceId": "2be02205766d435591be8a84deb706ca",
      "Freq": "35.212498",
      "ConsTotal": "133688.28",
      "1#冷机1#冷却水泵": "35.7375",
      "Name": "1#冷机1#冷却水泵"
    },
    {
      "P": "26.6",
      "Sta": "0.0",
      "DeviceId": "38970d193e974ff89d04faf506126c0f",
      "Freq": "35.212498",
      "ConsTotal": "133688.28",
      "1#冷机2#冷却水泵": "35.9921875",
      "Name": "1#冷机2#冷却水泵"
    },
    {
      "2#冷机1#冷却水泵": "1.55",
      "P": "0.0",
      "Sta": "0.0",
      "DeviceId": "200cdfcfb3744853a8e2a6c2797425b5",
      "Freq": "1.0875",
      "ConsTotal": "101248.12",
      "Name": "2#冷机1#冷却水泵"
    },
    {
      "P": "0.0",
      "Sta": "0.0",
      "DeviceId": "e3d9b831762a405d8be0438a3fb511e9",
      "Freq": "1.0875",
      "ConsTotal": "101248.12",
      "Name": "2#冷机2#冷却水泵"
    }
  ]
}